nrnsub/__init__.py
nrnsub/_worker.py
nrn_subprocess-1.3.4.dist-info/METADATA
nrn_subprocess-1.3.4.dist-info/WHEEL
nrn_subprocess-1.3.4.dist-info/top_level.txt
nrn_subprocess-1.3.4.dist-info/RECORD
