Metadata-Version: 2.1
Name: nrn-subprocess
Version: 1.3.4
Summary: Run isolated NEURON simulations in a single Python session.
Home-page: UNKNOWN
Author: Robin De Schepper
License: UNKNOWN
Platform: UNKNOWN
Requires-Dist: dill
Requires-Dist: tblib
